Metadata-Version: 2.1
Name: rabbitmq-metrics-to-graphite
Version: 0.5
Summary: https://github.com/orachide/rabbitmq-metrics-to-graphite
Home-page: https://github.com/orachide/rabbitmq-metrics-to-graphite
Author: Rachide Ouattara
Author-email: ouattchidi@gmail.com
License: BSD
Download-URL: https://github.com/orachide/rabbitmq-metrics-to-graphite/archive/0.5.tar.gz
Keywords: RabbitMQ Graphite Metrics
Platform: UNKNOWN
